gag_python/VERSION
gag_python/__init__.py
gag_python/gag.py
gag_python/conf/config.yaml
gag_python/models/age_deploy.prototxt
gag_python/models/age_net.caffemodel
gag_python/models/gender_deploy.prototxt
gag_python/models/gender_net.caffemodel
gag_python/models/opencv_face_detector.pbtxt
gag_python/models/opencv_face_detector_uint8.pb
gag_python-1.1.0.dist-info/LICENSE.md
gag_python-1.1.0.dist-info/METADATA
gag_python-1.1.0.dist-info/WHEEL
gag_python-1.1.0.dist-info/top_level.txt
gag_python-1.1.0.dist-info/RECORD
