Metadata-Version: 2.1
Name: gag-python
Version: 1.1.0
Summary: Predict you age by image!
Home-page: https://github.com/devProgst/gag-python
Author: Andrey Ivanov
Author-email: dev.progst@gmail.com
License: MIT
Platform: UNKNOWN
Classifier: License :: OSI Approved :: MIT License
Classifier: Intended Audience :: Developers
Classifier: Intended Audience :: Science/Research
Classifier: Programming Language :: Python
Classifier: Programming Language :: Python :: 3
Classifier: Programming Language :: Python :: Implementation :: PyPy
Classifier: Topic :: Software Development :: Libraries
Classifier: Topic :: Software Development :: Libraries :: Python Modules
Requires-Python: >=3.6.0
License-File: LICENSE.md
Requires-Dist: hydra-core (==1.1.1)
Requires-Dist: numpy (<=1.22,>=1.19.5)
Requires-Dist: opencv-python (<=4.5.5.64,>=4.5.1.48)
Requires-Dist: Pillow (<=8.4.0,>=8.1.2)
